immutableListType/__init__.py
immutableListType/immutableListType.py
immutableListType-1.0.0.dist-info/LICENSE
immutableListType-1.0.0.dist-info/METADATA
immutableListType-1.0.0.dist-info/WHEEL
immutableListType-1.0.0.dist-info/top_level.txt
immutableListType-1.0.0.dist-info/RECORD
