Metadata-Version: 2.1
Name: immutableListType
Version: 1.0.0
Summary: An Immutable List type for python.
Author-email: Roger Barker <pendletonroger@gmail.com>
Project-URL: Homepage, https://github.com/DJ-BBot/immutables
Project-URL: Bug Tracker, https://github.com/DJ-BBot/immutables/issues
Classifier: Programming Language :: Python :: 3
Classifier: License :: OSI Approved :: MIT License
Classifier: Operating System :: OS Independent
License-File: LICENSE
